ctdna/__init__.py
ctdna/bp_formulas.py
ctdna/ctdna.py
ctdna/detection.py
ctdna/examinations.py
ctdna/lesion.py
ctdna/lesions_sim.py
ctdna/roc.py
ctdna/sampling.py
ctdna/settings.py
ctdna/utils.py
ctdna/version.py
tests/test_bp_formulas.py
tests/test_detection.py
tests/test_example.py
tests/test_integration.py
tests/test_sampling.py
ctdna-0.1.2.dist-info/LICENSE.txt
ctdna-0.1.2.dist-info/METADATA
ctdna-0.1.2.dist-info/WHEEL
ctdna-0.1.2.dist-info/entry_points.txt
ctdna-0.1.2.dist-info/top_level.txt
ctdna-0.1.2.dist-info/RECORD
