Metadata-Version: 2.1
Name: ctdna
Version: 0.1.2
Summary: ctdna computes the expected tumor detection size at a given sampling frequency.
Home-page: https://github.com/reiterlab/ctdna
Author: Translational Cancer Evolution Laboratory @Stanford
Author-email: johannes.reiter@stanford.edu
License: GNUv3
Keywords: ctdna,cancer,cancer early detection,cancer screening,treatment monitoring
Platform: UNKNOWN
Classifier: Development Status :: 3 - Alpha
Classifier: Programming Language :: Python :: 3.6
Requires-Dist: numpy
Requires-Dist: scipy
Requires-Dist: pandas
Requires-Dist: matplotlib
Provides-Extra: plotting
Requires-Dist: matplotlib ; extra == 'plotting'
Requires-Dist: seaborn ; extra == 'plotting'
Requires-Dist: jupyter ; extra == 'plotting'
